catppuccin_jupyterlab/__init__.py
catppuccin_jupyterlab/_version.py
catppuccin_jupyterlab-0.2.3.data/data/share/jupyter/labextensions/catppuccin_jupyterlab/package.json
catppuccin_jupyterlab-0.2.3.data/data/share/jupyter/labextensions/catppuccin_jupyterlab/schemas/catppuccin_jupyterlab/package.json.orig
catppuccin_jupyterlab-0.2.3.data/data/share/jupyter/labextensions/catppuccin_jupyterlab/schemas/catppuccin_jupyterlab/plugin.json
catppuccin_jupyterlab-0.2.3.data/data/share/jupyter/labextensions/catppuccin_jupyterlab/static/649.728df92da9567b8e39fd.js
catppuccin_jupyterlab-0.2.3.data/data/share/jupyter/labextensions/catppuccin_jupyterlab/static/remoteEntry.d6dc2392b94aa44dfdf6.js
catppuccin_jupyterlab-0.2.3.data/data/share/jupyter/labextensions/catppuccin_jupyterlab/static/style.js
catppuccin_jupyterlab-0.2.3.data/data/share/jupyter/labextensions/catppuccin_jupyterlab/static/third-party-licenses.json
catppuccin_jupyterlab-0.2.3.data/data/share/jupyter/labextensions/catppuccin_jupyterlab/themes/catppuccin_jupyterlab/index.css
catppuccin_jupyterlab-0.2.3.data/data/share/jupyter/labextensions/catppuccin_jupyterlab/themes/catppuccin_jupyterlab/index.js
catppuccin_jupyterlab-0.2.3.data/data/share/jupyter/labextensions/catppuccin_jupyterlab/install.json
catppuccin_jupyterlab-0.2.3.dist-info/METADATA
catppuccin_jupyterlab-0.2.3.dist-info/WHEEL
catppuccin_jupyterlab-0.2.3.dist-info/licenses/LICENSE
catppuccin_jupyterlab-0.2.3.dist-info/RECORD
