Metadata-Version: 2.3
Name: catppuccin-jupyterlab
Version: 0.2.3
Dynamic: Keywords
Summary: 📊 Soothing pastel theme for JupyterLab.
Project-URL: Homepage, https://github.com/catppuccin/jupyterlab
Project-URL: Bug Tracker, https://github.com/catppuccin/jupyterlab/issues
Project-URL: Repository, https://github.com/catppuccin/jupyterlab.git
Author-email: Gabriel Magno <gabrielmagno1@gmail.com>
License: MIT License
License-File: LICENSE
Classifier: Framework :: Jupyter
Classifier: Framework :: Jupyter :: JupyterLab
Classifier: Framework :: Jupyter :: JupyterLab :: 4
Classifier: Framework :: Jupyter :: JupyterLab :: Extensions
Classifier: Framework :: Jupyter :: JupyterLab :: Extensions :: Prebuilt
Classifier: License :: OSI Approved :: BSD License
Classifier: Programming Language :: Python
Classifier: Programming Language :: Python :: 3
Classifier: Programming Language :: Python :: 3.8
Classifier: Programming Language :: Python :: 3.9
Classifier: Programming Language :: Python :: 3.10
Classifier: Programming Language :: Python :: 3.11
Requires-Python: >=3.8
